mirador_core/__init__.py
mirador_core/constraints/__init__.py
mirador_core/constraints/validator.py
mirador_core/context/__init__.py
mirador_core/context/manager.py
mirador_core/core/__init__.py
mirador_core/core/error_handling/__init__.py
mirador_core/core/error_handling/error_handler.py
mirador_core-2.1.3.dist-info/METADATA
mirador_core-2.1.3.dist-info/WHEEL
mirador_core-2.1.3.dist-info/top_level.txt
mirador_core-2.1.3.dist-info/RECORD
