Metadata-Version: 2.4
Name: mirador-core
Version: 2.1.3
Summary: Privacy-first AI orchestration - 64 agents running 100% locally with zero cloud dependencies (HIPAA-ready)
Home-page: https://github.com/guitargnarr/mirador
Author: Matthew David Scott
Author-email: matthewdscott7@gmail.com
Project-URL: Homepage, https://projectlavos.com
Project-URL: Documentation, https://mirador.projectlavos.com
Project-URL: Source, https://github.com/guitargnarr/mirador
Project-URL: Bug Tracker, https://github.com/guitargnarr/mirador/issues
Project-URL: API, https://mirador-xva2.onrender.com
Keywords: ai,llm,ollama,privacy,hipaa,local-ai,ai-agents,orchestration,healthcare-ai,mlops
Classifier: Development Status :: 4 - Beta
Classifier: Intended Audience :: Developers
Classifier: Topic :: Software Development :: Libraries :: Python Modules
Classifier: License :: OSI Approved :: MIT License
Classifier: Programming Language :: Python :: 3
Classifier: Programming Language :: Python :: 3.8
Classifier: Programming Language :: Python :: 3.9
Classifier: Programming Language :: Python :: 3.10
Classifier: Programming Language :: Python :: 3.11
Requires-Python: >=3.8
Provides-Extra: dev
Requires-Dist: pytest>=7.4.0; extra == "dev"
Requires-Dist: pytest-cov>=4.1.0; extra == "dev"
Requires-Dist: black>=23.0.0; extra == "dev"
Requires-Dist: flake8>=6.0.0; extra == "dev"
Requires-Dist: mypy>=1.5.0; extra == "dev"
Provides-Extra: ui
Requires-Dist: streamlit>=1.28.0; extra == "ui"
Requires-Dist: plotly>=5.18.0; extra == "ui"
Provides-Extra: web
Requires-Dist: gradio>=3.50.0; extra == "web"
Requires-Dist: fastapi>=0.100.0; extra == "web"
Requires-Dist: uvicorn>=0.23.0; extra == "web"
Provides-Extra: vector
Requires-Dist: chromadb>=0.4.0; extra == "vector"
Requires-Dist: sentence-transformers>=2.2.0; extra == "vector"
Provides-Extra: all
Requires-Dist: streamlit>=1.28.0; extra == "all"
Requires-Dist: plotly>=5.18.0; extra == "all"
Requires-Dist: chromadb>=0.4.0; extra == "all"
Requires-Dist: sentence-transformers>=2.2.0; extra == "all"
Requires-Dist: gradio>=3.50.0; extra == "all"
Requires-Dist: fastapi>=0.100.0; extra == "all"
Requires-Dist: uvicorn>=0.23.0; extra == "all"
Dynamic: author
Dynamic: author-email
Dynamic: classifier
Dynamic: description
Dynamic: description-content-type
Dynamic: home-page
Dynamic: keywords
Dynamic: project-url
Dynamic: provides-extra
Dynamic: requires-python
Dynamic: summary
